README
setup.py
tabledown/__init__.py
tabledown/licences.py
tabledown/tdxls.py
tabledown.egg-info/PKG-INFO
tabledown.egg-info/SOURCES.txt
tabledown.egg-info/dependency_links.txt
tabledown.egg-info/requires.txt
tabledown.egg-info/top_level.txt